LICENSE.txt
README.md
setup.py
Topsis_AVIRAL_102016049/__init__.py
Topsis_AVIRAL_102016049/topsis.py
Topsis_AVIRAL_102016049.egg-info/PKG-INFO
Topsis_AVIRAL_102016049.egg-info/SOURCES.txt
Topsis_AVIRAL_102016049.egg-info/dependency_links.txt
Topsis_AVIRAL_102016049.egg-info/requires.txt
Topsis_AVIRAL_102016049.egg-info/top_level.txt